{
  "category": "BEAUTY",
  "protectedMoments": [
    "사용 전 상태",
    "제품 양",
    "적용 방법",
    "사용 과정",
    "전후 비교",
    "실제 결과",
    "피부 또는 머리카락 디테일"
  ],
  "removableMoments": [],
  "preferredPacing": "FAST",
  "subtitleDensity": "MEDIUM",
  "preserveNaturalAudio": false,
  "preferredShotTypes": [
    "medium_close_up",
    "close_up",
    "detail"
  ],
  "discouragedSoundEffects": [],
  "safetyChecks": [
    "의학적 효능 생성 금지",
    "결과 보장 표현 금지",
    "과도한 피부 보정 금지"
  ],
  "shootingGuideRules": [
    "얼굴은 medium_close_up으로 촬영",
    "제품은 close_up으로 촬영",
    "피부와 질감은 detail로 촬영",
    "전후 비교는 같은 조명과 구도를 우선한다",
    "사용 전후는 같은 앵글을 유지"
  ]
}
